manga_py/__init__.py
manga_py/__main__.py
manga_py/download_methods.py
manga_py/fs.py
manga_py/info.py
manga_py/manga_image.py
manga_py/meta.py
manga_py/parser.py
manga_py/provider.py
manga_py/util.py
manga_py/base_classes/__init__.py
manga_py/base_classes/abstract.py
manga_py/base_classes/arc_name.py
manga_py/base_classes/archive.py
manga_py/base_classes/base.py
manga_py/base_classes/callbacks.py
manga_py/base_classes/chapter_helper.py
manga_py/base_classes/comic_info_builder.py
manga_py/base_classes/params.py
manga_py/base_classes/static.py
manga_py/base_classes/web_driver/__init__.py
manga_py/base_classes/web_driver/chrome.py
manga_py/base_classes/web_driver/firefox.py
manga_py/base_classes/web_driver/web_driver.py
manga_py/cli/__init__.py
manga_py/cli/_args_debug.py
manga_py/cli/_args_downloading.py
manga_py/cli/_args_general.py
manga_py/cli/_args_image.py
manga_py/cli/_args_reader.py
manga_py/cli/_requirements.py
manga_py/cli/args.py
manga_py/crypt/__init__.py
manga_py/crypt/ac_qq_com.py
manga_py/crypt/aes.js
manga_py/crypt/aes_zp.js
manga_py/crypt/base_lib.py
manga_py/crypt/bato_to_crypt.py
manga_py/crypt/hentainexus_com.py
manga_py/crypt/kissmanga_com.py
manga_py/crypt/mangago_me.py
manga_py/crypt/mangarock_com.py
manga_py/crypt/manhuagui_com.py
manga_py/crypt/puzzle.py
manga_py/crypt/sunday_webry_com.py
manga_py/crypt/viz_com.py
manga_py/default_config/__init__.py
manga_py/default_config/actions.py
manga_py/http/__init__.py
manga_py/http/auto_proxy.py
manga_py/http/cf_downloader.py
manga_py/http/flare_solver.py
manga_py/http/google_dcp.py
manga_py/http/multi_threads.py
manga_py/http/request.py
manga_py/http/updater.py
manga_py/http/url_normalizer.py
manga_py/http/websocket.py
manga_py/providers/18comic_org.py
manga_py/providers/1stkissmanga_com.py
manga_py/providers/_3asq_org.py
manga_py/providers/__init__.py
manga_py/providers/_template.py
manga_py/providers/ac_qq_com.py
manga_py/providers/acomics_ru.py
manga_py/providers/adulto_seinagi_org.py
manga_py-1.33.2.dist-info/LICENSE
manga_py-1.33.2.dist-info/METADATA
manga_py-1.33.2.dist-info/WHEEL
manga_py-1.33.2.dist-info/entry_points.txt
manga_py-1.33.2.dist-info/top_level.txt
manga_py-1.33.2.dist-info/RECORD
