Metadata-Version: 2.1
Name: manga-py
Version: 1.33.2
Summary: Universal assistant download manga.
Home-page: https://github.com/manga-py/manga-py
Author: Sergey Zharkov
Author-email: sttv-pc@mail.ru
License: MIT
Keywords: manga-downloader,manga,manga-py
Platform: UNKNOWN
Classifier: Development Status :: 5 - Production/Stable
Classifier: License :: OSI Approved :: MIT License
Classifier: Natural Language :: English
Classifier: Environment :: Console
Classifier: Programming Language :: Python :: 3.7
Classifier: Programming Language :: Python :: 3.8
Classifier: Programming Language :: Python :: 3.9
Classifier: Topic :: Internet :: WWW/HTTP
Requires-Python: >=3.7.1
License-File: LICENSE
Requires-Dist: cloudscraper
Requires-Dist: cssselect (>=1.1)
Requires-Dist: packaging (>=20.3)
Requires-Dist: progressbar2 (>=3.50)
Requires-Dist: pycryptodome (>=3.9)
Requires-Dist: PyExecJS (>=1.5)
Requires-Dist: requests (>=2.23)
Requires-Dist: better-exceptions (>=0.2)
Requires-Dist: pysocks (>=1.7)
Requires-Dist: toml (>=0.10)
